keylogger/__init__.py
keylogger/__version__.py
keylogger/keylogger.py
keylogger/pyxhook.py
keylogger-2.7.3.dist-info/METADATA
keylogger-2.7.3.dist-info/WHEEL
keylogger-2.7.3.dist-info/entry_points.txt
keylogger-2.7.3.dist-info/top_level.txt
keylogger-2.7.3.dist-info/RECORD
